AlmaIndicator/Alma.py
AlmaIndicator/__init__.py
AlmaIndicator-0.0.4.dist-info/LICENSE.txt
AlmaIndicator-0.0.4.dist-info/METADATA
AlmaIndicator-0.0.4.dist-info/WHEEL
AlmaIndicator-0.0.4.dist-info/top_level.txt
AlmaIndicator-0.0.4.dist-info/RECORD
